alibabacloud_apig20240327/__init__.py
alibabacloud_apig20240327/client.py
alibabacloud_apig20240327/models/__init__.py
alibabacloud_apig20240327/models/_add_gateway_security_group_rule_request.py
alibabacloud_apig20240327/models/_add_gateway_security_group_rule_response.py
alibabacloud_apig20240327/models/_add_gateway_security_group_rule_response_body.py
alibabacloud_apig20240327/models/_agent_service_config.py
alibabacloud_apig20240327/models/_ai_service_config.py
alibabacloud_apig20240327/models/_ak_sk_identity_config.py
alibabacloud_apig20240327/models/_api_key_identity_config.py
alibabacloud_apig20240327/models/_api_route_conflict_info.py
alibabacloud_apig20240327/models/_attachment.py
alibabacloud_apig20240327/models/_auth_config.py
alibabacloud_apig20240327/models/_authorization_resource_info.py
alibabacloud_apig20240327/models/_backend.py
alibabacloud_apig20240327/models/_batch_delete_consumer_authorization_rule_request.py
alibabacloud_apig20240327/models/_batch_delete_consumer_authorization_rule_response.py
alibabacloud_apig20240327/models/_batch_delete_consumer_authorization_rule_response_body.py
alibabacloud_apig20240327/models/_change_resource_group_request.py
alibabacloud_apig20240327/models/_change_resource_group_response.py
alibabacloud_apig20240327/models/_change_resource_group_response_body.py
alibabacloud_apig20240327/models/_check_service_linked_role_result.py
alibabacloud_apig20240327/models/_consumer_config.py
alibabacloud_apig20240327/models/_consumer_info.py
alibabacloud_apig20240327/models/_create_and_attach_policy_request.py
alibabacloud_apig20240327/models/_create_and_attach_policy_response.py
alibabacloud_apig20240327/models/_create_and_attach_policy_response_body.py
alibabacloud_apig20240327/models/_create_consumer_authorization_rule_request.py
alibabacloud_apig20240327/models/_create_consumer_authorization_rule_response.py
alibabacloud_apig20240327/models/_create_consumer_authorization_rule_response_body.py
alibabacloud_apig20240327-6.0.1.dist-info/LICENSE
alibabacloud_apig20240327-6.0.1.dist-info/METADATA
alibabacloud_apig20240327-6.0.1.dist-info/WHEEL
alibabacloud_apig20240327-6.0.1.dist-info/top_level.txt
alibabacloud_apig20240327-6.0.1.dist-info/RECORD
